24011902_mem.v
// BLM2022 Odev 3 - Bellek Modulleri
// Ogrenci: Omar Nuriyev - 24011902

// Komut bellegi (imem) - imem.mem dosyasindan yuklenir
module imem(
    input  wire [31:0] a,
    output wire [31:0] rd
);
    reg [31:0] RAM[63:0];

    initial begin
        $readmemh("imem.mem", RAM);
    end

    assign rd = RAM[a[31:2]];
endmodule

// Veri bellegi (dmem) - testbench tarafindan ilk degerler atanir
module dmem(
    input  wire        clk, we,
    input  wire [31:0] a, wd,
    output wire [31:0] rd
);
    reg [31:0] RAM[63:0];

    assign rd = RAM[a[31:2]];

    always @(posedge clk)
        if (we) RAM[a[31:2]] <= wd;
endmodule

24011902_riscv.v
// BLM2022 Odev 3 - Tek Cevrim RISC-V Islemci
// Ogrenci: Omar Nuriyev - 24011902
// Kaynak: Odev2 Soru1 (Q2) - lw,sw,add,sub,slt,or,and,beq,addi,slti,ori,andi,jal,srai

module riscv_core(
    input  wire        clk, reset,
    output wire [31:0] PC,
    input  wire [31:0] Instr,
    output wire        MemWrite,
    output wire [31:0] ALUResult, WriteData,
    input  wire [31:0] ReadData
);
    wire        ALUSrc, RegWrite, Jump, Zero;
    wire [1:0]  ResultSrc, ImmSrc;
    wire [2:0]  ALUControl;
    wire        PCSrc;

    controller c(
        .op(Instr[6:0]),
        .funct3(Instr[14:12]),
        .funct7b5(Instr[30]),
        .Zero(Zero),
        .ResultSrc(ResultSrc),
        .MemWrite(MemWrite),
        .PCSrc(PCSrc),
        .ALUSrc(ALUSrc),
        .RegWrite(RegWrite),
        .Jump(Jump),
        .ImmSrc(ImmSrc),
        .ALUControl(ALUControl)
    );

    datapath dp(
        .clk(clk),
        .reset(reset),
        .ResultSrc(ResultSrc),
        .PCSrc(PCSrc),
        .ALUSrc(ALUSrc),
        .RegWrite(RegWrite),
        .ImmSrc(ImmSrc),
        .ALUControl(ALUControl),
        .Zero(Zero),
        .PC(PC),
        .Instr(Instr),
        .ALUResult(ALUResult),
        .WriteData(WriteData),
        .ReadData(ReadData)
    );
endmodule

module controller(
    input  wire [6:0] op,
    input  wire [2:0] funct3,
    input  wire       funct7b5,
    input  wire       Zero,
    output wire [1:0] ResultSrc,
    output wire       MemWrite,
    output wire       PCSrc, ALUSrc,
    output wire       RegWrite, Jump,
    output wire [1:0] ImmSrc,
    output wire [2:0] ALUControl
);
    wire [1:0] ALUOp;
    wire       Branch;

    maindec md(
        .op(op),
        .ResultSrc(ResultSrc),
        .MemWrite(MemWrite),
        .Branch(Branch),
        .ALUSrc(ALUSrc),
        .RegWrite(RegWrite),
        .Jump(Jump),
        .ImmSrc(ImmSrc),
        .ALUOp(ALUOp)
    );

    aludec ad(
        .opb5(op[5]),
        .funct3(funct3),
        .funct7b5(funct7b5),
        .ALUOp(ALUOp),
        .ALUControl(ALUControl)
    );

    assign PCSrc = (Branch & Zero) | Jump;
endmodule

module maindec(
    input  wire [6:0] op,
    output reg  [1:0] ResultSrc,
    output reg        MemWrite,
    output reg        Branch, ALUSrc,
    output reg        RegWrite, Jump,
    output reg  [1:0] ImmSrc,
    output reg  [1:0] ALUOp
);
    always @(*) begin
        case(op)
            7'b0000011: begin // lw
                RegWrite=1; ImmSrc=2'b00; ALUSrc=1; MemWrite=0;
                ResultSrc=2'b01; Branch=0; ALUOp=2'b00; Jump=0;
            end
            7'b0100011: begin // sw
                RegWrite=0; ImmSrc=2'b01; ALUSrc=1; MemWrite=1;
                ResultSrc=2'b00; Branch=0; ALUOp=2'b00; Jump=0;
            end
            7'b0110011: begin // R-type
                RegWrite=1; ImmSrc=2'bxx; ALUSrc=0; MemWrite=0;
                ResultSrc=2'b00; Branch=0; ALUOp=2'b10; Jump=0;
            end
            7'b1100011: begin // beq
                RegWrite=0; ImmSrc=2'b10; ALUSrc=0; MemWrite=0;
                ResultSrc=2'b00; Branch=1; ALUOp=2'b01; Jump=0;
            end
            7'b0010011: begin // I-type ALU (addi, andi, ori, slti, srai)
                RegWrite=1; ImmSrc=2'b00; ALUSrc=1; MemWrite=0;
                ResultSrc=2'b00; Branch=0; ALUOp=2'b10; Jump=0;
            end
            7'b1101111: begin // jal
                RegWrite=1; ImmSrc=2'b11; ALUSrc=1'bx; MemWrite=0;
                ResultSrc=2'b10; Branch=0; ALUOp=2'bxx; Jump=1;
            end
            default: begin
                RegWrite=0; ImmSrc=2'b00; ALUSrc=0; MemWrite=0;
                ResultSrc=2'b00; Branch=0; ALUOp=2'b00; Jump=0;
            end
        endcase
    end
endmodule

module aludec(
    input  wire       opb5,
    input  wire [2:0] funct3,
    input  wire       funct7b5,
    input  wire [1:0] ALUOp,
    output reg  [2:0] ALUControl
);
    wire rtype_sub = funct7b5 & opb5;

    always @(*) begin
        case(ALUOp)
            2'b00: ALUControl = 3'b000; // add (lw/sw)
            2'b01: ALUControl = 3'b001; // sub (beq)
            2'b10: case(funct3)
                       3'b000: ALUControl = rtype_sub ? 3'b001 : 3'b000; // sub / add, addi
                       3'b010: ALUControl = 3'b101;                        // slt, slti
                       3'b110: ALUControl = 3'b011;                        // or, ori
                       3'b111: ALUControl = 3'b010;                        // and, andi
                       3'b101: ALUControl = funct7b5 ? 3'b100 : 3'bxxx;   // srai
                       default: ALUControl = 3'bxxx;
                   endcase
            default: ALUControl = 3'bxxx;
        endcase
    end
endmodule

module datapath(
    input  wire        clk, reset,
    input  wire [1:0]  ResultSrc,
    input  wire        PCSrc, ALUSrc,
    input  wire        RegWrite,
    input  wire [1:0]  ImmSrc,
    input  wire [2:0]  ALUControl,
    output wire        Zero,
    output wire [31:0] PC,
    input  wire [31:0] Instr,
    output wire [31:0] ALUResult, WriteData,
    input  wire [31:0] ReadData
);
    wire [31:0] PCNext, PCPlus4, PCTarget;
    wire [31:0] ImmExt;
    wire [31:0] SrcA, SrcB;
    wire [31:0] Result;

    flopr #(32) pcreg(clk, reset, PCNext, PC);
    adder       pcadd4(PC, 32'd4, PCPlus4);
    adder       pcaddbranch(PC, ImmExt, PCTarget);
    mux2 #(32)  pcmux(PCPlus4, PCTarget, PCSrc, PCNext);

    regfile     rf(clk, RegWrite, Instr[19:15], Instr[24:20],
                   Instr[11:7], Result, SrcA, WriteData);
    extend      ext(Instr[31:7], ImmSrc, ImmExt);

    mux2 #(32)  srcbmux(WriteData, ImmExt, ALUSrc, SrcB);
    alu         alu_inst(SrcA, SrcB, ALUControl, ALUResult, Zero);

    mux3 #(32)  resmux(ALUResult, ReadData, PCPlus4, ResultSrc, Result);
endmodule

module regfile(
    input  wire        clk,
    input  wire        we3,
    input  wire [ 4:0] a1, a2, a3,
    input  wire [31:0] wd3,
    output wire [31:0] rd1, rd2
);
    reg [31:0] rf[31:0];

    always @(posedge clk)
        if (we3) rf[a3] <= wd3;

    assign rd1 = (a1 != 0) ? rf[a1] : 32'b0;
    assign rd2 = (a2 != 0) ? rf[a2] : 32'b0;
endmodule

module extend(
    input  wire [31:7] instr,
    input  wire [1:0]  immsrc,
    output reg  [31:0] immext
);
    always @(*) begin
        case(immsrc)
            2'b00: immext = {{20{instr[31]}}, instr[31:20]};
            2'b01: immext = {{20{instr[31]}}, instr[31:25], instr[11:7]};
            2'b10: immext = {{20{instr[31]}}, instr[7], instr[30:25], instr[11:8], 1'b0};
            2'b11: immext = {{12{instr[31]}}, instr[19:12], instr[20], instr[30:21], 1'b0};
            default: immext = 32'bx;
        endcase
    end
endmodule

module alu(
    input  wire [31:0] a, b,
    input  wire [2:0]  alucontrol,
    output reg  [31:0] result,
    output wire        zero
);
    always @(*) begin
        case(alucontrol)
            3'b000: result = a + b;
            3'b001: result = a - b;
            3'b010: result = a & b;
            3'b011: result = a | b;
            3'b100: result = $signed(a) >>> b[4:0]; // srai
            3'b101: result = ($signed(a) < $signed(b)) ? 32'b1 : 32'b0;
            default: result = 32'bx;
        endcase
    end
    assign zero = (result == 32'b0);
endmodule

module adder(
    input  wire [31:0] a, b,
    output wire [31:0] y
);
    assign y = a + b;
endmodule

module mux2 #(parameter WIDTH = 32) (
    input  wire [WIDTH-1:0] d0, d1,
    input  wire             s,
    output wire [WIDTH-1:0] y
);
    assign y = s ? d1 : d0;
endmodule

module mux3 #(parameter WIDTH = 32) (
    input  wire [WIDTH-1:0] d0, d1, d2,
    input  wire [1:0]       s,
    output wire [WIDTH-1:0] y
);
    assign y = s[1] ? d2 : (s[0] ? d1 : d0);
endmodule

module flopr #(parameter WIDTH = 32) (
    input  wire             clk, reset,
    input  wire [WIDTH-1:0] d,
    output reg  [WIDTH-1:0] q
);
    always @(posedge clk or posedge reset)
        if (reset) q <= 0;
        else       q <= d;
endmodule

24011902_top.v
// BLM2022 Odev 3 - Ust Seviye Modul
// Ogrenci: Omar Nuriyev - 24011902

module top(
    input  wire        clk, reset,
    output wire [31:0] WriteData, DataAdr,
    output wire        MemWrite
);
    wire [31:0] PC, Instr, ReadData;

    riscv_core riscv(
        .clk(clk),
        .reset(reset),
        .PC(PC),
        .Instr(Instr),
        .MemWrite(MemWrite),
        .ALUResult(DataAdr),
        .WriteData(WriteData),
        .ReadData(ReadData)
    );

    imem imem(
        .a(PC),
        .rd(Instr)
    );

    dmem dmem(
        .clk(clk),
        .we(MemWrite),
        .a(DataAdr),
        .wd(WriteData),
        .rd(ReadData)
    );
endmodule

24011902_tb.v
`timescale 1ns/1ps
// BLM2022 Odev 3 - Testbench
// Ogrenci: Omar Nuriyev - 24011902
//
// Bellek duzeni (dmem):
//   Adres 0x00-0x4C : ARRAY[0..19]
//   Adres 0x50      : MASK = 0x55555555
//   Adres 0x54-0xA0 : COUNT[0..19] (program tarafindan yazilacak)
//
// Cevrim sayisi (tek cevrimli islemci):
//   - Her eleman icin: 109 cevrim (sabit, ic dongu her zaman 16 kez calisir)
//   - 20 eleman toplam: 5 (init) + 20*109 + 1 (son beq) + 1 (halt) = 2187 cevrim

module tb();
    reg         clk;
    reg         reset;
    wire [31:0] WriteData, DataAdr;
    wire        MemWrite;

    integer i, pass_count, cycle_count;

    // Beklenen COUNT degerleri (dogrulama icin)
    reg [31:0] expected_count [0:19];

    top dut(clk, reset, WriteData, DataAdr, MemWrite);

    // VCD dosyasi
    initial begin
        $dumpfile("24011902.vcd");
        $dumpvars(0, tb);
    end

    // Beklenen degerler
    initial begin
        expected_count[0]  = 32'd0;
        expected_count[1]  = 32'd1;
        expected_count[2]  = 32'd0;
        expected_count[3]  = 32'd1;
        expected_count[4]  = 32'd0;
        expected_count[5]  = 32'd7;
        expected_count[6]  = 32'd9;
        expected_count[7]  = 32'd8;
        expected_count[8]  = 32'd8;
        expected_count[9]  = 32'd16;
        expected_count[10] = 32'd16;
        expected_count[11] = 32'd15;
        expected_count[12] = 32'd9;
        expected_count[13] = 32'd10;
        expected_count[14] = 32'd7;
        expected_count[15] = 32'd8;
        expected_count[16] = 32'd7;
        expected_count[17] = 32'd8;
        expected_count[18] = 32'd10;
        expected_count[19] = 32'd2;
    end

    // dmem'i ARRAY ve MASK ile ilklendir
    initial begin
        // ARRAY[0..19]
        dut.dmem.RAM[0]  = 32'h00000000;
        dut.dmem.RAM[1]  = 32'h00000001;
        dut.dmem.RAM[2]  = 32'h00000200;
        dut.dmem.RAM[3]  = 32'h00400000;
        dut.dmem.RAM[4]  = 32'h80000000;
        dut.dmem.RAM[5]  = 32'h51C06460;
        dut.dmem.RAM[6]  = 32'hDEC287D9;
        dut.dmem.RAM[7]  = 32'h6C896594;
        dut.dmem.RAM[8]  = 32'h99999999;
        dut.dmem.RAM[9]  = 32'hFFFFFFFF;
        dut.dmem.RAM[10] = 32'h7FFFFFFF;
        dut.dmem.RAM[11] = 32'hFFFFFFFE;
        dut.dmem.RAM[12] = 32'hC7B52169;
        dut.dmem.RAM[13] = 32'h8CEFF731;
        dut.dmem.RAM[14] = 32'hA550921E;
        dut.dmem.RAM[15] = 32'h0DB01F33;
        dut.dmem.RAM[16] = 32'h24BB7B48;
        dut.dmem.RAM[17] = 32'h98513914;
        dut.dmem.RAM[18] = 32'hCD76ED30;
        dut.dmem.RAM[19] = 32'hC0000003;
        // MASK = 0x55555555 (adres 0x50 = word 20)
        dut.dmem.RAM[20] = 32'h55555555;
        // COUNT alani sifirla (word 21-40)
        for (i = 21; i <= 40; i = i + 1)
            dut.dmem.RAM[i] = 32'h00000000;
    end

    // Reset ve zaman asimi
    initial begin
        pass_count  = 0;
        cycle_count = 0;
        reset = 1; clk = 0;
        #22; reset = 0;
        // Maksimum 25000 ns (2500 cevrim @ 10ns) bekle
        #25000;
        $display("ZAMAN ASIMI: Simülasyon tamamlanamadi.");
        $finish;
    end

    // 100 MHz saat (10 ns periyot)
    always #5 clk = ~clk;

    // Cevrim sayaci
    always @(posedge clk)
        if (!reset) cycle_count = cycle_count + 1;

    // SW yazma gozlemcisi
    always @(negedge clk) begin
        if (MemWrite) begin
            // COUNT dizisi: adres 0x54-0xA0 (84-160)
            if (DataAdr >= 32'd84 && DataAdr <= 32'd160) begin
                i = (DataAdr - 32'd84) >> 2;
                if (WriteData === expected_count[i])
                    $display("COUNT[%0d] = %0d  DOGRU  (adres=0x%0h, cevrim=%0d)",
                             i, WriteData, DataAdr, cycle_count);
                else
                    $display("COUNT[%0d] = %0d  YANLIS! (beklenen=%0d, adres=0x%0h)",
                             i, WriteData, expected_count[i], DataAdr);
                pass_count = pass_count + 1;
                if (pass_count == 20) begin
                    #20;
                    $display("");
                    $display("=== SONUCLAR ===");
                    $display("Tüm 20 COUNT degeri hesaplandi.");
                    $display("Toplam cevrim sayisi (son COUNT yazimina kadar): %0d", cycle_count);
                    $display("Her eleman icin cevrim sayisi: 109 (sabit, ic dongu her zaman 16 kez)");
                    $display("");
                    $display("Sira  ARRAY       COUNT  Durum");
                    for (i = 0; i < 20; i = i + 1)
                        $display("%2d    0x%08h  %2d     %s",
                                 i+1,
                                 dut.dmem.RAM[i],
                                 dut.dmem.RAM[21+i],
                                 (dut.dmem.RAM[21+i] === expected_count[i]) ? "PASS" : "FAIL");
                    $finish;
                end
            end
        end
    end

endmodule

24011902.vcd
$date
	Thu Jun  4 03:14:14 2026
$end
$version
	Icarus Verilog
$end
$timescale
	1ps
$end
$scope module tb $end
$var wire 32 ! WriteData [31:0] $end
$var wire 1 " MemWrite $end
$var wire 32 # DataAdr [31:0] $end
$var reg 1 $ clk $end
$var reg 1 % reset $end
$var integer 32 & cycle_count [31:0] $end
$var integer 32 ' i [31:0] $end
$var integer 32 ( pass_count [31:0] $end
$scope module dut $end
$var wire 1 $ clk $end
$var wire 1 % reset $end
$var wire 32 ) WriteData [31:0] $end
$var wire 32 * ReadData [31:0] $end
$var wire 32 + PC [31:0] $end
$var wire 1 " MemWrite $end
$var wire 32 , Instr [31:0] $end
$var wire 32 - DataAdr [31:0] $end
$scope module dmem $end
$var wire 1 $ clk $end
$var wire 32 . rd [31:0] $end
$var wire 1 " we $end
$var wire 32 / wd [31:0] $end
$var wire 32 0 a [31:0] $end
$upscope $end
$scope module imem $end
$var wire 32 1 rd [31:0] $end
$var wire 32 2 a [31:0] $end
$upscope $end
$scope module riscv $end
$var wire 32 3 Instr [31:0] $end
$var wire 32 4 ReadData [31:0] $end
$var wire 1 $ clk $end
$var wire 1 % reset $end
$var wire 1 5 Zero $end
$var wire 32 6 WriteData [31:0] $end
$var wire 2 7 ResultSrc [1:0] $end
$var wire 1 8 RegWrite $end
$var wire 1 9 PCSrc $end
$var wire 32 : PC [31:0] $end
$var wire 1 " MemWrite $end
$var wire 1 ; Jump $end
$var wire 2 < ImmSrc [1:0] $end
$var wire 1 = ALUSrc $end
$var wire 32 > ALUResult [31:0] $end
$var wire 3 ? ALUControl [2:0] $end
$scope module c $end
$var wire 1 9 PCSrc $end
$var wire 3 @ funct3 [2:0] $end
$var wire 1 A funct7b5 $end
$var wire 7 B op [6:0] $end
$var wire 1 5 Zero $end
$var wire 2 C ResultSrc [1:0] $end
$var wire 1 8 RegWrite $end
$var wire 1 " MemWrite $end
$var wire 1 ; Jump $end
$var wire 2 D ImmSrc [1:0] $end
$var wire 1 E Branch $end
$var wire 1 = ALUSrc $end
$var wire 2 F ALUOp [1:0] $end
$var wire 3 G ALUControl [2:0] $end
$scope module ad $end
$var wire 3 H funct3 [2:0] $end
$var wire 1 A funct7b5 $end
$var wire 1 I opb5 $end
$var wire 1 J rtype_sub $end
$var wire 2 K ALUOp [1:0] $end
$var reg 3 L ALUControl [2:0] $end
$upscope $end
$scope module md $end
$var wire 7 M op [6:0] $end
$var reg 2 N ALUOp [1:0] $end
$var reg 1 = ALUSrc $end
$var reg 1 E Branch $end
$var reg 2 O ImmSrc [1:0] $end
$var reg 1 ; Jump $end
$var reg 1 " MemWrite $end
$var reg 1 8 RegWrite $end
$var reg 2 P ResultSrc [1:0] $end
$upscope $end
$upscope $end
$scope module dp $end
$var wire 3 Q ALUControl [2:0] $end
$var wire 1 = ALUSrc $end
$var wire 2 R ImmSrc [1:0] $end
$var wire 32 S Instr [31:0] $end
$var wire 1 9 PCSrc $end
$var wire 32 T ReadData [31:0] $end
$var wire 1 8 RegWrite $end
$var wire 2 U ResultSrc [1:0] $end
$var wire 1 $ clk $end
$var wire 1 % reset $end
$var wire 1 5 Zero $end
$var wire 32 V WriteData [31:0] $end
$var wire 32 W SrcB [31:0] $end
$var wire 32 X SrcA [31:0] $end
$var wire 32 Y Result [31:0] $end
$var wire 32 Z PCTarget [31:0] $end
$var wire 32 [ PCPlus4 [31:0] $end
$var wire 32 \ PCNext [31:0] $end
$var wire 32 ] PC [31:0] $end
$var wire 32 ^ ImmExt [31:0] $end
$var wire 32 _ ALUResult [31:0] $end
$scope module alu_inst $end
$var wire 3 ` alucontrol [2:0] $end
$var wire 1 5 zero $end
$var wire 32 a b [31:0] $end
$var wire 32 b a [31:0] $end
$var reg 32 c result [31:0] $end
$upscope $end
$scope module ext $end
$var wire 2 d immsrc [1:0] $end
$var wire 25 e instr [31:7] $end
$var reg 32 f immext [31:0] $end
$upscope $end
$scope module pcadd4 $end
$var wire 32 g b [31:0] $end
$var wire 32 h y [31:0] $end
$var wire 32 i a [31:0] $end
$upscope $end
$scope module pcaddbranch $end
$var wire 32 j b [31:0] $end
$var wire 32 k y [31:0] $end
$var wire 32 l a [31:0] $end
$upscope $end
$scope module pcmux $end
$var wire 32 m d0 [31:0] $end
$var wire 32 n d1 [31:0] $end
$var wire 1 9 s $end
$var wire 32 o y [31:0] $end
$var parameter 32 p WIDTH $end
$upscope $end
$scope module pcreg $end
$var wire 1 $ clk $end
$var wire 32 q d [31:0] $end
$var wire 1 % reset $end
$var parameter 32 r WIDTH $end
$var reg 32 s q [31:0] $end
$upscope $end
$scope module resmux $end
$var wire 32 t d0 [31:0] $end
$var wire 32 u d1 [31:0] $end
$var wire 32 v d2 [31:0] $end
$var wire 2 w s [1:0] $end
$var wire 32 x y [31:0] $end
$var parameter 32 y WIDTH $end
$upscope $end
$scope module rf $end
$var wire 5 z a1 [4:0] $end
$var wire 5 { a2 [4:0] $end
$var wire 5 | a3 [4:0] $end
$var wire 1 $ clk $end
$var wire 32 } wd3 [31:0] $end
$var wire 1 8 we3 $end
$var wire 32 ~ rd2 [31:0] $end
$var wire 32 !" rd1 [31:0] $end
$upscope $end
$scope module srcbmux $end
$var wire 32 "" d0 [31:0] $end
$var wire 32 #" d1 [31:0] $end
$var wire 1 = s $end
$var wire 32 $" y [31:0] $end
$var parameter 32 %" WIDTH $end
$upscope $end
$upscope $end
$upscope $end
$upscope $end
$upscope $end
$enddefinitions $end
$comment Show the parameter values. $end
$dumpall
b100000 %"
b100000 y
b100000 r
b100000 p
$end
#0
$dumpvars
b0 $"
b0 #"
b0 ""
b0 !"
b0 ~
b0 }
b1010 |
b0 {
b0 z
b0 x
b0 w
b100 v
b0 u
b0 t
b0 s
b100 q
b100 o
b0 n
b100 m
b0 l
b0 k
b0 j
b0 i
b100 h
b100 g
b0 f
b1010 e
b0 d
b0 c
b0 b
b0 a
b0 `
b0 _
b0 ^
b0 ]
b100 \
b100 [
b0 Z
b0 Y
b0 X
b0 W
b0 V
b0 U
b0 T
b10100010011 S
b0 R
b0 Q
b0 P
b0 O
b10 N
b10011 M
b0 L
b10 K
0J
0I
b0 H
b0 G
b10 F
0E
b0 D
b0 C
b10011 B
0A
b0 @
b0 ?
b0 >
1=
b0 <
0;
b0 :
09
18
b0 7
b0 6
15
b0 4
b10100010011 3
b0 2
b10100010011 1
b0 0
b0 /
b0 .
b0 -
b10100010011 ,
b0 +
b0 *
b0 )
b0 (
b101001 '
b0 &
1%
0$
b0 #
0"
b0 !
$end
#5000
1$
#10000
0$
#15000
1$
#20000
0$
#22000
0%
#25000
b1010100 Y
b1010100 x
b1010100 }
05
b1010100 #
b1010100 -
b1010100 0
b1010100 >
b1010100 _
b1010100 c
b1010100 t
b1010100 W
b1010100 a
b1010100 $"
bx !
bx )
bx /
bx 6
bx V
bx ~
bx ""
b1010100 ^
b1010100 f
b1010100 j
b1010100 #"
b10100 {
b1011 |
b10101000000000001011 e
b1000 \
b1000 o
b1000 q
b101010000000000010110010011 ,
b101010000000000010110010011 1
b101010000000000010110010011 3
b101010000000000010110010011 S
b1011000 Z
b1011000 k
b1011000 n
b1000 [
b1000 h
b1000 m
b1000 v
b100 +
b100 2
b100 :
b100 ]
b100 i
b100 l
b100 s
b1 &
1$
#30000
0$
#35000
b1010101010101010101010101010101 *
b1010101010101010101010101010101 .
b1010101010101010101010101010101 4
b1010101010101010101010101010101 T
b1010101010101010101010101010101 u
b1010101010101010101010101010101 Y
b1010101010101010101010101010101 x
b1010101010101010101010101010101 }
b1010000 #
b1010000 -
b1010000 0
b1010000 >
b1010000 _
b1010000 c
b1010000 t
b1010000 W
b1010000 a
b1010000 $"
b0 F
b0 K
b0 N
b1 7
b1 C
b1 P
b1 U
b1 w
b0 ?
b0 G
b0 L
b0 Q
b0 `
b1010000 ^
b1010000 f
b1010000 j
b1010000 #"
b11 B
b11 M
b10 @
b10 H
b10000 {
b11111 |
b10100000000001011111 e
b1100 \
b1100 o
b1100 q
b101000000000010111110000011 ,
b101000000000010111110000011 1
b101000000000010111110000011 3
b101000000000010111110000011 S
b1011000 Z
b1011000 k
b1011000 n
b1100 [
b1100 h
b1100 m
b1100 v
b1000 +
b1000 2
b1000 :
b1000 ]
b1000 i
b1000 l
b1000 s
b10 &
1$
#40000
0$
#45000
b0 Y
b0 x
b0 }
b0 *
b0 .
b0 4
b0 T
b0 u
15
b0 #
b0 -
b0 0
b0 >
b0 _
b0 c
b0 t
b0 W
b0 a
b0 $"
b10 F
b10 K
b10 N
b0 7
b0 C
b0 P
b0 U
b0 w
b0 !
b0 )
b0 /
b0 6
b0 V
b0 ~
b0 ""
b0 ^
b0 f
b0 j
b0 #"
b10011 B
b10011 M
b0 @
b0 H
b0 {
b1000 |
b1000 e
b10000 \
b10000 o
b10000 q
b10000010011 ,
b10000010011 1
b10000010011 3
b10000010011 S
b1100 Z
b1100 k
b1100 n
b10000 [
b10000 h
b10000 m
b10000 v
b1100 +
b1100 2
b1100 :
b1100 ]
b1100 i
b1100 l
b1100 s
b11 &
1$
#50000
0$
#55000
b10100 Y
b10100 x
b10100 }
b1010001110000000110010001100000 *
b1010001110000000110010001100000 .
b1010001110000000110010001100000 4
b1010001110000000110010001100000 T
b1010001110000000110010001100000 u
05
b10100 #
b10100 -
b10100 0
b10100 >
b10100 _
b10100 c
b10100 t
b10100 W
b10100 a
b10100 $"
bx !
bx )
bx /
bx 6
bx V
bx ~
bx ""
b10100 ^
b10100 f
b10100 j
b10100 #"
b10100 {
b11101 |
b101000000000011101 e
b10100 \
b10100 o
b10100 q
b1010000000000111010010011 ,
b1010000000000111010010011 1
b1010000000000111010010011 3
b1010000000000111010010011 S
b100100 Z
b100100 k
b100100 n
b10100 [
b10100 h
b10100 m
b10100 v
b10000 +
b10000 2
b10000 :
b10000 ]
b10000 i
b10000 l
b10000 s
b100 &
1$
#60000
0$
#65000
b11111111111111111111111111101100 Y
b11111111111111111111111111101100 x
b11111111111111111111111111101100 }
bx *
bx .
bx 4
bx T
bx u
b11111111111111111111111111101100 #
b11111111111111111111111111101100 -
b11111111111111111111111111101100 0
b11111111111111111111111111101100 >
b11111111111111111111111111101100 _
b11111111111111111111111111101100 c
b11111111111111111111111111101100 t
b1 ?
b1 G
b1 L
b1 Q
b1 `
1I
b1 F
b1 K
b1 N
1E
0=
b10 <
b10 D
b10 O
b10 R
b10 d
08
b10100 !
b10100 )
b10100 /
b10100 6
b10100 V
b10100 ~
b10100 ""
b1001000 ^
b1001000 f
b1001000 j
b1001000 #"
b1100011 B
b1100011 M
b1000 z
b11101 {
b1000 |
b10111010100000001000 e
b11000 \
b11000 o
b11000 q
b101110101000000010001100011 ,
b101110101000000010001100011 1
b101110101000000010001100011 3
b101110101000000010001100011 S
b1011100 Z
b1011100 k
b1011100 n
b11000 [
b11000 h
b11000 m
b11000 v
b10100 +
b10100 2
b10100 :
b10100 ]
b10100 i
b10100 l
b10100 s
b101 &
1$
#70000
0$
#75000
b0 Y
b0 x
b0 }
b0 *
b0 .
b0 4
b0 T
b0 u
15
b0 #
b0 -
b0 0
b0 >
b0 _
b0 c
b0 t
b0 ?
b0 G
b0 L
b0 Q
b0 `
b0 W
b0 a
b0 $"
b10 F
b10 K
b10 N
0E
bx <
bx D
bx O
bx R
bx d
18
b0 !
b0 )
b0 /
b0 6
b0 V
b0 ~
b0 ""
bx ^
bx f
bx j
bx #"
b110011 B
b110011 M
b1000 {
b110 |
b10000100000000110 e
b11100 \
b11100 o
b11100 q
b100001000000001100110011 ,
b100001000000001100110011 1
b100001000000001100110011 3
b100001000000001100110011 S
bx Z
bx k
bx n
b11100 [
b11100 h
b11100 m
b11100 v
b11000 +
b11000 2
b11000 :
b11000 ]
b11000 i
b11000 l
b11000 s
b110 &
1$
#80000
0$
#85000
b110 z
b110 {
b1100011000000110 e
b100000 \
b100000 o
b100000 q
b11000110000001100110011 ,
b11000110000001100110011 1
b11000110000001100110011 3
b11000110000001100110011 S
b100000 [
b100000 h
b100000 m
b100000 v
b11100 +
b11100 2
b11100 :
b11100 ]
b11100 i
b11100 l
b11100 s
b111 &
1$
#90000
0$
#95000
b1010 z
b111 |
b1100101000000111 e
b100100 \
b100100 o
b100100 q
b11001010000001110110011 ,
b11001010000001110110011 1
b11001010000001110110011 3
b11001010000001110110011 S
b100100 [
b100100 h
b100100 m
b100100 v
b100000 +
b100000 2
b100000 :
b100000 ]
b100000 i
b100000 l
b100000 s
b1000 &
1$
#100000
0$
#105000
b100100 Z
b100100 k
b100100 n
b0 ^
b0 f
b0 j
b0 #"
0I
b0 F
b0 K
b0 N
b1 7
b1 C
b1 P
b1 U
b1 w
1=
b0 <
b0 D
b0 O
b0 R
b0 d
b0 ?
b0 G
b0 L
b0 Q
b0 `
b11 B
b11 M
b10 @
b10 H
b111 z
b0 {
b10010 |
b11101010010 e
b101000 \
b101000 o
b101000 q
b111010100100000011 ,
b111010100100000011 1
b111010100100000011 3
b111010100100000011 S
b101000 [
b101000 h
b101000 m
b101000 v
b100100 +
b100100 2
b100100 :
b100100 ]
b100100 i
b100100 l
b100100 s
b1001 &
1$
#110000
0$
#115000
b10 ?
b10 G
b10 L
b10 Q
b10 `
b1010101010101010101010101010101 W
b1010101010101010101010101010101 a
b1010101010101010101010101010101 $"
1I
b10 F
b10 K
b10 N
b0 7
b0 C
b0 P
b0 U
b0 w
0=
bx <
bx D
bx O
bx R
bx d
b1010101010101010101010101010101 !
b1010101010101010101010101010101 )
b1010101010101010101010101010101 /
b1010101010101010101010101010101 6
b1010101010101010101010101010101 V
b1010101010101010101010101010101 ~
b1010101010101010101010101010101 ""
bx ^
bx f
bx j
bx #"
b110011 B
b110011 M
b111 @
b111 H
b10010 z
b11111 {
b111111001011110010 e
b101100 \
b101100 o
b101100 q
b1111110010111100100110011 ,
b1111110010111100100110011 1
b1111110010111100100110011 3
b1111110010111100100110011 S
bx Z
bx k
bx n
b101100 [
b101100 h
b101100 m
b101100 v
b101000 +
b101000 2
b101000 :
b101000 ]
b101000 i
b101000 l
b101000 s
b1010 &
1$
#120000
0$
#125000
b0 Y
b0 x
b0 }
b0 *
b0 .
b0 4
b0 T
b0 u
b101100 Z
b101100 k
b101100 n
b0 ^
b0 f
b0 j
b0 #"
15
b0 #
b0 -
b0 0
b0 >
b0 _
b0 c
b0 t
b0 W
b0 a
b0 $"
0I
1=
b0 <
b0 D
b0 O
b0 R
b0 d
b0 ?
b0 G
b0 L
b0 Q
b0 `
b0 !
b0 )
b0 /
b0 6
b0 V
b0 ~
b0 ""
b10011 B
b10011 M
b0 @
b0 H
b0 z
b0 {
b10011 |
b10011 e
b110000 \
b110000 o
b110000 q
b100110010011 ,
b100110010011 1
b100110010011 3
b100110010011 S
b110000 [
b110000 h
b110000 m
b110000 v
b101100 +
b101100 2
b101100 :
b101100 ]
b101100 i
b101100 l
b101100 s
b1011 &
1$
#130000
0$
#135000
b10000 Y
b10000 x
b10000 }
b10000000000000000000000000000000 *
b10000000000000000000000000000000 .
b10000000000000000000000000000000 4
b10000000000000000000000000000000 T
b10000000000000000000000000000000 u
05
b10000 #
b10000 -
b10000 0
b10000 >
b10000 _
b10000 c
b10000 t
b10000 W
b10000 a
b10000 $"
bx !
bx )
bx /
bx 6
bx V
bx ~
bx ""
b10000 ^
b10000 f
b10000 j
b10000 #"
b10000 {
b10100 |
b100000000000010100 e
b110100 \
b110100 o
b110100 q
b1000000000000101000010011 ,
b1000000000000101000010011 1
b1000000000000101000010011 3
b1000000000000101000010011 S
b1000000 Z
b1000000 k
b1000000 n
b110100 [
b110100 h
b110100 m
b110100 v
b110000 +
b110000 2
b110000 :
b110000 ]
b110000 i
b110000 l
b110000 s
b1100 &
1$
#140000
0$
